{"name":"Localstoragejs","tagline":"Local storage Javascript and CSS files.No 304 request.","body":"localStorageJS\r\n==============\r\n\r\nLocal storage Javascript and CSS files.No 304 request.\r\n\r\n##Usage\r\n###The lsJS.js file.\r\n```javascript\r\nvar lsJS = function() {\r\n    \"use strict\";\r\n    var run_lsJS = {\r\n        config:{},\r\n        load:function(){\r\n            var a = arguments, r = false,\r\n            lteIE8 = eval(!-[1,]),\r\n            h = document.head || document.getElementsByTagName('head')[0],\r\n            ss = this.ss,\r\n            config = this.config,\r\n            d = document.createElement('script');\r\n            d.type = 'text/javascript';\r\n            if(typeof window.localStorage != 'undefined' && localStorage.getItem('localStorageJS') && !config.debug) {\r\n                var lsCode = localStorage.getItem('localStorageJS'),\r\n                lsJS_info;\r\n                try{\r\n                    lsJS_info = JSON.parse(lsCode);\r\n                } catch(e) {\r\n                }\r\n                if(lsJS_info && lsJS_info.url && (lsJS_info.url == ss)) {\r\n                    r = true;\r\n                    if(lteIE8) {\r\n                        d.text = lsJS_info.source;\r\n                    } else {\r\n                        d.textContent = lsJS_info.source;\r\n                    }\r\n                    h.appendChild(d);\r\n                    localStorageJS.config(config);\r\n                    localStorageJS.load(a);\r\n                } else {\r\n                    localStorage.removeItem('localStorageJS');\r\n                }\r\n            }\r\n            if(!r) {\r\n                d.src = ss;\r\n                d.onload = d.onreadystatechange = function() {\r\n                    if(!r && (!this.readyState || this.readyState == \"loaded\" || this.readyState == \"complete\")) {\r\n                        r = true;\r\n                        localStorageJS.config(config);\r\n                        localStorageJS.load(a);\r\n                        //d.parentNode.removeChild(d);\r\n                        d.onload = d.onreadystatechange = null;\r\n                    }\r\n                };\r\n                h.appendChild(d);\r\n            }\r\n        }\r\n    };\r\n    return run_lsJS;\r\n}();\r\n\r\nlsJS.version = '0.1.6';\r\n/* Custom settings */\r\n  lsJS.ss = 'localStorageJS.js';\r\n  lsJS.config.error_expires = 30;\r\n  lsJS.config.removeAll = false;\r\n  lsJS.config.allready = function() {\r\n      $(function() {\r\n          $(\"#global_loading\").hide();\r\n      });\r\n  };\r\n  lsJS.load({\r\n      name: \"jquery\",\r\n      url: \"jquery-1.11.1.min.js\",\r\n      version: \"1.11.1\"\r\n  },{\r\n      name: \"history\",\r\n      url: \"history.js\",\r\n      require:\"jquery\"\r\n  },{\r\n      name: \"console\",\r\n      url: \"console.js\",\r\n      router:{\r\n          path:\"console.html\"\r\n      }\r\n  });\r\n```\r\n##Demo\r\nhttp://localstoragejs.org/demo/index.html\r\n","google":"","note":"Don't delete this file! It's used internally to help with page regeneration."}